snakemake_executor_plugin_drmaa/__init__.py
snakemake_executor_plugin_drmaa-0.1.5.dist-info/LICENSE
snakemake_executor_plugin_drmaa-0.1.5.dist-info/METADATA
snakemake_executor_plugin_drmaa-0.1.5.dist-info/WHEEL
snakemake_executor_plugin_drmaa-0.1.5.dist-info/RECORD
