Metadata-Version: 2.1
Name: snakemake-executor-plugin-drmaa
Version: 0.1.5
Summary: A snakemake executor plugin for submission of jobs via DRMAA.
Home-page: https://github.com/snakemake/snakemake-executor-plugin-drmaa
License: MIT
Keywords: snakemake,plugin,executor,cluster,drmaa
Author: Johannes Koester
Author-email: johannes.koester@uni-due.de
Requires-Python: >=3.11,<4.0
Classifier: License :: OSI Approved :: MIT License
Classifier: Programming Language :: Python :: 3
Classifier: Programming Language :: Python :: 3.11
Classifier: Programming Language :: Python :: 3.12
Requires-Dist: drmaa (>=0.7.9,<0.8.0)
Requires-Dist: snakemake-interface-common (>=1.13.0,<2.0.0)
Requires-Dist: snakemake-interface-executor-plugins (>=9.0.0,<10.0.0)
Project-URL: Documentation, https://snakemake.github.io/snakemake-plugin-catalog/plugins/executor/drmaa.html
Project-URL: Repository, https://github.com/snakemake/snakemake-executor-plugin-drmaa
